setup.cfg
setup.py
etherwatch/__init__.py
etherwatch/__main__.py
etherwatch/api_keys_sample.py
etherwatch/db_functions.py
etherwatch/ether_functions.py
etherwatch/messaging_functions.py
etherwatch/positions_sample.py
etherwatch.egg-info/PKG-INFO
etherwatch.egg-info/SOURCES.txt
etherwatch.egg-info/dependency_links.txt
etherwatch.egg-info/requires.txt
etherwatch.egg-info/top_level.txt