Metadata-Version: 1.1
Name: etherwatch
Version: 0.1.6
Summary: Notifies you about ether prices.
Home-page: http://github.com/theculliganman/ether_watch
Author: Ryan Culligan
Author-email: rrculligan@gmail.com
License: MIT
Download-URL: https://codeload.github.com/TheCulliganMan/ether_watch/archive/master.tar.gz
Keywords: ether,ethereum,coinbase
Platform: UNKNOWN
